pytest_mockito/__init__.py
pytest_mockito/plugin.py
pytest_mockito-0.0.5.dist-info/METADATA
pytest_mockito-0.0.5.dist-info/WHEEL
pytest_mockito-0.0.5.dist-info/entry_points.txt
pytest_mockito-0.0.5.dist-info/licenses/LICENSE
pytest_mockito-0.0.5.dist-info/RECORD
