Metadata-Version: 2.4
Name: pytest-mockito
Version: 0.0.5
Summary: Base fixtures for mockito
Project-URL: Homepage, https://github.com/kaste/pytest-mockito
Author-email: herr kaste <herr.kaste@gmail.com>
License: MIT
License-File: LICENSE
Classifier: Development Status :: 5 - Production/Stable
Classifier: Intended Audience :: Developers
Classifier: License :: OSI Approved :: MIT License
Classifier: Operating System :: MacOS :: MacOS X
Classifier: Operating System :: Microsoft :: Windows
Classifier: Operating System :: POSIX
Classifier: Programming Language :: Python
Classifier: Topic :: Software Development :: Quality Assurance
Classifier: Topic :: Software Development :: Testing
Classifier: Topic :: Utilities
Requires-Python: >=3.8
Requires-Dist: mockito>=1.0.6
Requires-Dist: pytest>=6
